{
    "header":  {
                   "description":  "소상공인시장진흥공단 사각형내 상가업소정보",
                   "columns":  [
                                   "상가업소번호",
                                   "상호명",
                                   "지점명",
                                   "상권업종대분류코드",
                                   "상권업종대분류명",
                                   "상권업종중분류코드",
                                   "상권업종중분류명",
                                   "상권업종소분류코드",
                                   "상권업종소분류명",
                                   "표준산업분류코드",
                                   "표준산업분류명",
                                   "시도코드",
                                   "시도명",
                                   "시군구코드",
                                   "시군구명",
                                   "행정동코드",
                                   "행정동명",
                                   "법정동코드",
                                   "법정동명",
                                   "PNU코드",
                                   "대지구분코드",
                                   "대지구분명",
                                   "지번본번지",
                                   "지번부번지",
                                   "지번주소",
                                   "도로명코드",
                                   "도로명",
                                   "건물본번지",
                                   "건물부번지",
                                   "건물관리번호",
                                   "건물명",
                                   "도로명주소",
                                   "구우편번호",
                                   "신우편번호",
                                   "동정보",
                                   "층정보",
                                   "호정보",
                                   "경도",
                                   "위도"
                               ],
                   "stdrYm":  "202512",
                   "resultCode":  "00",
                   "resultMsg":  "NORMAL SERVICE"
               },
    "body":  {
                 "items":  [
                               {
                                   "bizesId":  "MA010120220809803147",
                                   "bizesNm":  "흙처럼나무처럼",
                                   "brchNm":  "",
                                   "indsLclsCd":  "G2",
                                   "indsLclsNm":  "소매",
                                   "indsMclsCd":  "G205",
                                   "indsMclsNm":  "식료품 소매",
                                   "indsSclsCd":  "G20501",
                                   "indsSclsNm":  "곡물/곡분 소매업",
                                   "ksicCd":  "G47211",
                                   "ksicNm":  "곡물, 곡분 및 가축 사료 소매업",
                                   "ctprvnCd":  "47",
                                   "ctprvnNm":  "경상북도",
                                   "signguCd":  "47770",
                                   "signguNm":  "영덕군",
                                   "adongCd":  "47770380",
                                   "adongNm":  "창수면",
                                   "ldongCd":  "4777038041",
                                   "ldongNm":  "창수면",
                                   "lnoCd":  "4777038041106010000",
                                   "plotSctCd":  "1",
                                   "plotSctNm":  "대지",
                                   "lnoMnno":  601,
                                   "lnoSlno":  "",
                                   "lnoAdr":  "경상북도 영덕군 창수면 오촌리 601",
                                   "rdnmCd":  "477704754472",
                                   "rdnm":  "경상북도 영덕군 창수면 오촌1길",
                                   "bldMnno":  81,
                                   "bldSlno":  6,
                                   "bldMngNo":  "4777038041106010000000001",
                                   "bldNm":  "",
                                   "rdnmAdr":  "경상북도 영덕군 창수면 오촌1길 81-6",
                                   "oldZipcd":  "766871",
                                   "newZipcd":  "36400",
                                   "dongNo":  "",
                                   "flrNo":  "",
                                   "hoNo":  "",
                                   "lon":  129.313266967849,
                                   "lat":  36.6099948257081
                               },
                               {
                                   "bizesId":  "MA010120220800538949",
                                   "bizesNm":  "오촌칠보산한옥민박한호당",
                                   "brchNm":  "",
                                   "indsLclsCd":  "I1",
                                   "indsLclsNm":  "숙박",
                                   "indsMclsCd":  "I101",
                                   "indsMclsNm":  "일반 숙박",
                                   "indsSclsCd":  "I10103",
                                   "indsSclsNm":  "펜션",
                                   "ksicCd":  "I55104",
                                   "ksicNm":  "민박업",
                                   "ctprvnCd":  "47",
                                   "ctprvnNm":  "경상북도",
                                   "signguCd":  "47770",
                                   "signguNm":  "영덕군",
                                   "adongCd":  "47770380",
                                   "adongNm":  "창수면",
                                   "ldongCd":  "4777038041",
                                   "ldongNm":  "창수면",
                                   "lnoCd":  "4777038041104160002",
                                   "plotSctCd":  "1",
                                   "plotSctNm":  "대지",
                                   "lnoMnno":  416,
                                   "lnoSlno":  2,
                                   "lnoAdr":  "경상북도 영덕군 창수면 오촌리 416-2",
                                   "rdnmCd":  "477704754472",
                                   "rdnm":  "경상북도 영덕군 창수면 오촌1길",
                                   "bldMnno":  43,
                                   "bldSlno":  12,
                                   "bldMngNo":  "4777038041104160002003944",
                                   "bldNm":  "",
                                   "rdnmAdr":  "경상북도 영덕군 창수면 오촌1길 43-12",
                                   "oldZipcd":  "766871",
                                   "newZipcd":  "36400",
                                   "dongNo":  "",
                                   "flrNo":  "",
                                   "hoNo":  "",
                                   "lon":  129.316353613711,
                                   "lat":  36.6089528258741
                               }
                           ],
                 "numOfRows":  100,
                 "pageNo":  1,
                 "totalCount":  2
             }
}
